INSTALL.rst
MANIFEST.in
README.rst
setup.py
data/pytg.xml
data/pytuga-avatar.svg
data/pytuga-logo.png
data/pytuga-simple-logo.svg
data/pytuga.desktop
data/pytuga.lang
data/icons/logo-32x32.png
data/icons/logo-64x64.png
data/icons/pytuga.svg
data/icons/text-x-pytuga.svg
data/mime/pynguin.mime
data/mime/pynguin.sharedmimeinfo
src/pytuga/__init__.py
src/pytuga/__main__.py
src/pytuga/curses.py
src/pytuga/keywords.py
src/pytuga/lexer.py
src/pytuga/transpyler.py
src/pytuga.egg-info/PKG-INFO
src/pytuga.egg-info/SOURCES.txt
src/pytuga.egg-info/dependency_links.txt
src/pytuga.egg-info/entry_points.txt
src/pytuga.egg-info/not-zip-safe
src/pytuga.egg-info/pbr.json
src/pytuga.egg-info/requires.txt
src/pytuga.egg-info/top_level.txt