Metadata-Version: 1.1
Name: pytuga
Version: 0.13.0
Summary: Interpretador de Pytuguês: um Python com sotaque lusitano.
Home-page: https://github.com/transpyler/pytuga
Author: Fábio Macêdo Mendes
Author-email: fabiomacedomendes@gmail.com
License: UNKNOWN
Platform: UNKNOWN
Classifier: Development Status :: 4 - Beta
Classifier: Intended Audience :: Developers
Classifier: License :: OSI Approved :: GNU General Public License (GPL)
Classifier: Operating System :: POSIX
Classifier: Programming Language :: Python
Classifier: Topic :: Software Development :: Libraries
